pyxel_physics_engine-0.1.2.dist-info/licenses/LICENSE
pyxphys/__init__.py
pyxphys/app.py
pyxphys/collision.py
pyxphys/engine.py
pyxphys/resolver.py
pyxphys/spatial.py
pyxphys/utils.py
pyxphys/world.py
pyxel_physics_engine-0.1.2.dist-info/METADATA
pyxel_physics_engine-0.1.2.dist-info/WHEEL
pyxel_physics_engine-0.1.2.dist-info/top_level.txt
pyxel_physics_engine-0.1.2.dist-info/RECORD
