Metadata-Version: 2.4
Name: pyxel-physics-engine
Version: 0.1.2
Summary: GameObject and Physics framework for Pyxel
Author-email: Hishi057 <Hiratsuka512@icloud.com>
License: MIT License
Project-URL: Homepage, https://github.com/Hishi057/Pyxel-Physics-Engine
Classifier: License :: OSI Approved :: MIT License
License-File: LICENSE
Requires-Dist: pyxel
Dynamic: license-file
